apolo_cli/__init__.py
apolo_cli/__main__.py
apolo_cli/admin.py
apolo_cli/ael.py
apolo_cli/alias.py
apolo_cli/app_template.py
apolo_cli/apps.py
apolo_cli/asyncio_utils.py
apolo_cli/blob_storage.py
apolo_cli/click_types.py
apolo_cli/completion.py
apolo_cli/config.py
apolo_cli/const.py
apolo_cli/defaults.py
apolo_cli/disks.py
apolo_cli/docker_credential_helper.py
apolo_cli/file_logging.py
apolo_cli/image.py
apolo_cli/job.py
apolo_cli/log_formatter.py
apolo_cli/main.py
apolo_cli/parse_utils.py
apolo_cli/plugin.py
apolo_cli/py.typed
apolo_cli/root.py
apolo_cli/secrets.py
apolo_cli/service_accounts.py
apolo_cli/share.py
apolo_cli/stats.py
apolo_cli/storage.py
apolo_cli/topics.py
apolo_cli/utils.py
apolo_cli/formatters/__init__.py
apolo_cli/formatters/admin.py
apolo_cli/formatters/app_templates.py
apolo_cli/formatters/app_values.py
apolo_cli/formatters/apps.py
apolo_cli/formatters/blob_storage.py
apolo_cli/formatters/bucket_credentials.py
apolo_cli/formatters/buckets.py
apolo_cli/formatters/config.py
apolo_cli/formatters/disks.py
apolo_cli/formatters/images.py
apolo_cli/formatters/jobs.py
apolo_cli/formatters/secrets.py
apolo_cli/formatters/service_accounts.py
apolo_cli/formatters/storage.py
apolo_cli/formatters/utils.py
neuro_cli-25.5.0.dist-info/licenses/LICENSE
neuro_cli-25.5.0.dist-info/METADATA
neuro_cli-25.5.0.dist-info/WHEEL
neuro_cli-25.5.0.dist-info/entry_points.txt
neuro_cli-25.5.0.dist-info/top_level.txt
neuro_cli-25.5.0.dist-info/RECORD
